
{"header" : {
  "cloc_url"           : "github.com/AlDanial/cloc",
  "cloc_version"       : "1.90",
  "elapsed_seconds"    : 0.124375104904175,
  "n_files"            : 171,
  "n_lines"            : 44622,
  "files_per_second"   : 1374.87321222159,
  "lines_per_second"   : 358769.546641823},
"XML" :{
  "nFiles": 7,
  "blank": 3768,
  "comment": 0,
  "code": 20088},
"PHP" :{
  "nFiles": 35,
  "blank": 1893,
  "comment": 3516,
  "code": 7232},
"Bourne Shell" :{
  "nFiles": 69,
  "blank": 1155,
  "comment": 665,
  "code": 2812},
"Markdown" :{
  "nFiles": 22,
  "blank": 470,
  "comment": 0,
  "code": 1226},
"YAML" :{
  "nFiles": 15,
  "blank": 116,
  "comment": 113,
  "code": 549},
"JSON" :{
  "nFiles": 12,
  "blank": 1,
  "comment": 0,
  "code": 470},
"Dockerfile" :{
  "nFiles": 1,
  "blank": 64,
  "comment": 127,
  "code": 201},
"SVG" :{
  "nFiles": 5,
  "blank": 0,
  "comment": 1,
  "code": 40},
"JavaScript" :{
  "nFiles": 1,
  "blank": 0,
  "comment": 0,
  "code": 33},
"Python" :{
  "nFiles": 1,
  "blank": 9,
  "comment": 1,
  "code": 33},
"HTML" :{
  "nFiles": 2,
  "blank": 4,
  "comment": 0,
  "code": 17},
"INI" :{
  "nFiles": 1,
  "blank": 4,
  "comment": 5,
  "code": 9},
"SUM": {
  "blank": 7484,
  "comment": 4428,
  "code": 32710,
  "nFiles": 171} }
